[{"IdCliente":1,"Cpf":"11111111111","Nome":"Teste 01 ","Endereco":"rua teste","Telefone":"111111111","SituacaoCliente":"ativo","DataCadastro":"2018-12-02 09:39:42","DataAtualizado":"2018-12-02 09:39:42","EmDebito":"S"},{"IdCliente":2,"Cpf":"22222222222","Nome":"Teste 02","Endereco":"Rua Teste 2","Telefone":"222222222","SituacaoCliente":"ativo","DataCadastro":"2018-12-02 09:40:15","DataAtualizado":"2018-12-02 09:40:15","EmDebito":"N"},{"IdCliente":3,"Cpf":"33333333333","Nome":"Teste 03 ","Endereco":"Rua Teste 3","Telefone":"33333333","SituacaoCliente":"inativo","DataCadastro":"2018-12-02 09:40:54","DataAtualizado":"2018-12-02 09:40:54","EmDebito":"n"}]
